pylabcontrol/__init__.py
pylabcontrol/core/__init__.py
pylabcontrol/core/helper_functions.py
pylabcontrol/core/instrument.py
pylabcontrol/core/loading.py
pylabcontrol/core/parameter.py
pylabcontrol/core/probe.py
pylabcontrol/core/read_probes.py
pylabcontrol/core/read_write_functions.py
pylabcontrol/core/script.py
pylabcontrol/core/script_iterator.py
pylabcontrol/data_processing/__init__.py
pylabcontrol/data_processing/signal_processing.py
pylabcontrol/gui/__init__.py
pylabcontrol/gui/launch_gui.py
pylabcontrol/gui/compiled_ui_files/__init__.py
pylabcontrol/gui/compiled_ui_files/basic_application_window.py
pylabcontrol/gui/compiled_ui_files/load_dialog.py
pylabcontrol/gui/ui_files/basic_application_window.ui
pylabcontrol/gui/ui_files/import_window.ui
pylabcontrol/gui/ui_files/load_dialog.ui
pylabcontrol/gui/ui_files/manual_fitting_window.ui
pylabcontrol/gui/ui_files/manual_fitting_window_ensemble.ui
pylabcontrol/gui/windows_and_widgets/__init__.py
pylabcontrol/gui/windows_and_widgets/export_dialog.py
pylabcontrol/gui/windows_and_widgets/load_dialog.py
pylabcontrol/gui/windows_and_widgets/load_dialog_probes.py
pylabcontrol/gui/windows_and_widgets/main_window.py
pylabcontrol/gui/windows_and_widgets/manual_fitting.py
pylabcontrol/gui/windows_and_widgets/manual_fitting_ensemble.py
pylabcontrol/gui/windows_and_widgets/widgets.py
pylabcontrol/instruments/__init__.py
pylabcontrol/instruments/example_instrument.py
pylabcontrol/scripts/__init__.py
pylabcontrol/scripts/example_scripts.py
pylabcontrol/scripts/script_wait.py
pylabcontrol/scripts/select_points.py
pylabcontrol/tools/__init__.py
pylabcontrol/tools/export_default.py
pylabcontrol/tools/scan_serial_ports.py
pylabcontrol-0.1a20.dist-info/METADATA
pylabcontrol-0.1a20.dist-info/RECORD
pylabcontrol-0.1a20.dist-info/WHEEL
pylabcontrol-0.1a20.dist-info/entry_points.txt
pylabcontrol-0.1a20.dist-info/top_level.txt
tests/__init__.py
tests/test_helper_functions.py
tests/test_instrument.py
tests/test_parameter.py
tests/test_probe.py
tests/test_qt_widgets.py
tests/test_script.py
tests/test_script_iterator.py
tests/test_tools.py
