Metadata-Version: 2.1
Name: pylabcontrol
Version: 0.1a20
Summary: Python Laboratory Control Software
Home-page: https://github.com/LISE-B26/pylabcontrol
Author: Arthur Safira, Jan Gieseler, and Aaron Kabcenell
Author-email: b26lab@hotmail.com
License: GPL
Keywords: laboratory experiment control
Platform: UNKNOWN
Classifier: Programming Language :: Python :: 3.6
Classifier: License :: OSI Approved :: GNU General Public License v3 (GPLv3)
Classifier: Development Status :: 4 - Beta
Classifier: Environment :: Win32 (MS Windows)
Requires-Dist: matplotlib
Requires-Dist: pandas
Requires-Dist: numpy
Requires-Dist: scipy
Requires-Dist: pyyaml
Requires-Dist: PyQt5
